keynet/__init__.py
keynet/main.py
keynet-0.1.1.dist-info/licenses/LICENSE
keynet-0.1.1.dist-info/METADATA
keynet-0.1.1.dist-info/WHEEL
keynet-0.1.1.dist-info/top_level.txt
keynet-0.1.1.dist-info/RECORD
