Metadata-Version: 2.4
Name: keynet
Version: 0.1.1
Summary: Event-driven automation library for keyboard, mouse, system, and network events.
Author-email: Rudransh Joshi <rudransh20septmber@gmail.com>
License: MIT
Requires-Python: >=3.9
License-File: LICENSE
Requires-Dist: psutil
Requires-Dist: pynput
Requires-Dist: comtypes
Requires-Dist: pycaw
Dynamic: license-file
